LICENSE
README.md
pyproject.toml
setup.cfg
setup.py
./construction_site/__init__.py
./construction_site/construction_site.py
./construction_site/parse_functions.py
construction_site/__init__.py
construction_site/construction_site.py
construction_site/parse_functions.py
construction_site.egg-info/PKG-INFO
construction_site.egg-info/SOURCES.txt
construction_site.egg-info/dependency_links.txt
construction_site.egg-info/requires.txt
construction_site.egg-info/top_level.txt