Metadata-Version: 2.1
Name: construction-site
Version: 0.0.2
Summary: A usable and scalable API for RDF construction.
Home-page: https://github.com/viaacode/constructionsite
Author: Miel Vander Sande
Author-email: miel.vandersande@meemoo.be
License: MIT
Project-URL: Bug Tracker, https://github.com/viaacode/constructionsite/issues
Platform: UNKNOWN
Classifier: Development Status :: 1 - Planning
Classifier: Intended Audience :: Information Technology
Classifier: License :: OSI Approved :: MIT License
Classifier: Operating System :: POSIX :: Linux
Classifier: Programming Language :: Python :: 3
Classifier: Programming Language :: Python :: 3.4
Classifier: Programming Language :: Python :: 3.5
Requires-Python: >=3.6
